gradient_steps.cpython-36m-darwin.so
ridge/__init__.py
ridge/core.py
ridge/models/__init__.py
ridge/models/factorization_machine.py
ridge/models/factorization_machines.py
ridge/models/learning2rank.py
ridge/models/logit_models.py
ridge/models/matrix_factorization.py
ridge/models/softrank.py
ridge/preprocess/__init__.py
ridge/preprocess/vectorize.py
ridge/racer/gradient_steps.cpython-36m-darwin.so
ridge/racer/link_functions.cpython-36m-darwin.so
ridge/racer/loss_calculators.cpython-36m-darwin.so
ridge/racer/predictors.cpython-36m-darwin.so
ridge-0.0.6.dist-info/DESCRIPTION.rst
ridge-0.0.6.dist-info/METADATA
ridge-0.0.6.dist-info/RECORD
ridge-0.0.6.dist-info/WHEEL
ridge-0.0.6.dist-info/metadata.json
ridge-0.0.6.dist-info/top_level.txt
