Metadata-Version: 2.0
Name: ridge
Version: 0.0.6
Summary: Python Machine Learning Library specialized in L2R and Recommendation.
Home-page: https://github.com/moriaki3193/ridge
Author: Moriaki Saigusa
Author-email: moriaki3193@gmail.com
License: Type license() to see the full license text
Platform: UNKNOWN
Requires-Dist: numpy
Requires-Dist: scipy
Requires-Dist: tqdm
